{"story":{"group_1":[{"bg":"bg_adv_12061.jpg","bgm":"bgm01_battle04","chara":[{"cheek":0,"face":"mtn_ex_021.exp.json","id":100200,"motion":0,"mouthOpen":0,"pos":0},{"cheek":0,"face":"mtn_ex_020.exp.json","id":100300,"motion":200,"mouthOpen":1,"pos":2}],"nameLeft":"Yachiyo","nameRight":"Tsuruno","textRight":"[flashEffect:flashWhite1][bgEffect:shakeSmall][se:8000_flame_01_s]Hyah, hah, hyaaah!","turnChangeIn":"fadeIn","turnChangeOut":"fadeOut"},{"bgEffect":"shakeSmall","chara":[{"cheek":0,"id":100200,"motion":201,"mouthOpen":1}],"flashEffect":"flashWhite1","textBg":"shout","textLeft":"Hmph![se:4050_landing_jump]"},{"bg":"bg_adv_12061.jpg","chara":[{"cheek":0,"face":"mtn_ex_030.exp.json","id":101000,"motion":300,"mouthOpen":0,"pos":2}],"nameRight":"Momoko","textRight":"Wow, Tsuruno's pretty tough...","turnChangeIn":"rollInFast","turnChangeOut":"rollOutFast"},{"chara":[{"cheek":0,"face":"mtn_ex_030.exp.json","id":101100,"motion":0,"mouthOpen":0,"pos":0}],"nameLeft":"Kaede","textLeft":"I can barely even follow the action..."},{"chara":[{"cheek":0,"face":"mtn_ex_020.exp.json","id":100900,"motion":0,"mouthOpen":0,"pos":2}],"nameRight":"Rena","textRight":"Yachiyo's keeping up with her, though..."},{"bg":"bg_adv_12061.jpg","bgEffect":"shakeSmall","chara":[{"cheek":0,"face":"mtn_ex_021.exp.json","id":100200,"motion":0,"mouthOpen":0,"pos":0},{"cheek":0,"face":"mtn_ex_021.exp.json","id":100300,"motion":200,"mouthOpen":1,"pos":2}],"flashEffect":"flashWhite1","nameLeft":"Yachiyo","nameRight":"Tsuruno","textBg":"shout","textRight":"Hya![se:8000_flame_01_s]","turnChangeIn":"rollInFast","turnChangeOut":"rollOutFast"},{"chara":[{"cheek":0,"face":"mtn_ex_030.exp.json","id":100200,"mouthOpen":0}],"textLeft":"Phew...@You're something else."},{"chara":[{"cheek":0,"face":"mtn_ex_001.exp.json","id":100300,"motion":100,"mouthOpen":0}],"textRight":"I could say the same to you...@But all you've done is defend!"},{"bgEffect":"shakeSmall","chara":[{"cheek":0,"face":"mtn_ex_021.exp.json","id":100300,"motion":201,"mouthOpen":1}],"flashEffect":"flashWhite1","textBg":"shout","textRight":"[se:8000_flame_01_s]And you'll NEVER win like that!"},{"bgEffect":"shakeSmall","chara":[{"cheek":0,"effect":"shake","face":"mtn_ex_060.exp.json","id":100200,"motion":301,"mouthOpen":0}],"flashEffect":"flashRed1","textLeft":"Ungh![se:8001_flame_01_v]"},{"bg":"bg_adv_12061.jpg","chara":[{"cheek":0,"face":"mtn_ex_050.exp.json","id":100900,"motion":0,"mouthOpen":0,"pos":0},{"cheek":0,"face":"mtn_ex_050.exp.json","id":101100,"motion":0,"mouthOpen":1,"pos":2}],"nameLeft":"Rena","nameRight":"Kaede","textRight":"Yachiyo, no!","turnChangeIn":"rollInFast","turnChangeOut":"rollOutFast"},{"chara":[{"cheek":0,"id":100900,"motion":400,"mouthOpen":0}],"textLeft":"She's been hit!"},{"bg":"bg_adv_12061.jpg","chara":[{"cheek":0,"face":"mtn_ex_030.exp.json","id":100200,"motion":0,"mouthOpen":0,"pos":0},{"cheek":0,"face":"mtn_ex_011.exp.json","id":100300,"motion":200,"mouthOpen":0,"pos":2}],"nameLeft":"Yachiyo","nameRight":"Tsuruno","textRight":"Haha! [chara:100300:lipSynch_0][freeze:1][chara:100300:cheek_1][chara:100300:face_mtn_ex_020.exp.json][chara:100300:lipSynch_1]How about THAT!@Hehehe!","turnChangeIn":"rollInFast","turnChangeOut":"rollOutFast"},{"chara":[{"face":"mtn_ex_020.exp.json","id":100300,"mouthOpen":0}],"textRight":"Now then, time for the finishing blow!"},{"chara":[{"cheek":0,"face":"mtn_ex_021.exp.json","id":100200,"motion":201,"mouthOpen":0}],"textLeft":"...It's not over yet!"},{"chara":[{"cheek":0,"face":"mtn_ex_011.exp.json","id":100300,"motion":0,"mouthOpen":0}],"textRight":"Good!@I'm all fired up, too!"},{"chara":[{"cheek":0,"face":"mtn_ex_051.exp.json","id":100200,"lipSynch":0,"motion":0,"mouthOpen":0}],"textLeft":"(This girl is stronger than I thought...!)","turnEffect":"thinking"},{"chara":[{"cheek":0,"face":"mtn_ex_042.exp.json","id":100200,"lipSynch":0,"mouthOpen":0}],"textLeft":"(I won't be able to @beat her in a fair fight...)"},{"bgEffect":"shakeLarge","chara":[{"cheek":0,"face":"mtn_ex_021.exp.json","id":100300,"motion":101,"mouthOpen":1}],"flashEffect":"flashWhite2","textBg":"shout","textRight":"[se:4051_landing_throw]Take this, and this, and THIS!","turnEffect":"stop"},{"bgEffect":"shakeLarge","chara":[{"cheek":0,"effect":"shake","face":"mtn_ex_060.exp.json","id":100200,"motion":400,"mouthOpen":0}],"flashEffect":"flashRed2","textLeft":"[se:8002_flame_01_h]Hngh!"},{"bgEffect":"shakeLarge","chara":[{"cheek":0,"face":"mtn_ex_001.exp.json","id":100300,"motion":200,"mouthOpen":0}],"flashEffect":"flashWhite2","textRight":"[se:4051_landing_throw]Hyah!"},{"bgEffect":"shakeLarge","chara":[{"cheek":0,"effect":"shake","id":100200,"motion":400,"mouthOpen":0}],"flashEffect":"flashRed2","textLeft":"Ngh...!@[se:8002_flame_01_h][chara:100200:lipSynch_0][freeze:1.5][chara:100200:cheek_0][chara:100200:face_mtn_ex_051.exp.json][chara:100200:lipSynch_1]This... This is bad!"},{"bgEffect":"shakeLarge","chara":[{"cheek":0,"face":"mtn_ex_021.exp.json","id":100300,"motion":201,"mouthOpen":1}],"flashEffect":"flashWhite2","textBg":"shout","textRight":"[se:4051_landing_throw]You're open!@HYAAAAAAH!"},{"bg":"bg_adv_12061.jpg","chara":[{"cheek":0,"face":"mtn_ex_050.exp.json","id":100900,"motion":0,"mouthOpen":0,"pos":0},{"cheek":0,"face":"mtn_ex_020.exp.json","id":101000,"motion":200,"mouthOpen":0,"pos":2}],"nameLeft":"Rena","nameRight":"Momoko","textRight":"Oh, crud!","turnChangeIn":"rollInFast","turnChangeOut":"rollOutFast"},{"chara":[{"cheek":0,"id":100900,"motion":400,"mouthOpen":1}],"textLeft":"Yachiyo!"},{"bg":"bg_adv_12061.jpg","bgEffect":"shakeLarge","chara":[{"cheek":0,"face":"mtn_ex_011.exp.json","id":100300,"motion":100,"mouthOpen":0,"pos":2},{"cheek":0,"face":"mtn_ex_060.exp.json","id":100200,"motion":0,"mouthOpen":0,"pos":0,"tear":0}],"flashEffect":"flashRed2","nameLeft":"Yachiyo","nameRight":"Tsuruno","textRight":"[se:8002_flame_01_h]It's over!@I beat you![chara:100200:effect_shake]","turnChangeIn":"rollInFast","turnChangeOut":"rollOutFast"},{"chara":[{"cheek":0,"face":"mtn_ex_050.exp.json","id":100300,"motion":0,"mouthOpen":0},{"cheek":0,"effect":"fadeout","id":100200}],"textRight":"Huh...?@She's[chara:100300:lipSynch_0][freeze:0.5][chara:100300:cheek_0][chara:100300:face_mtn_ex_030.exp.json][chara:100300:lipSynch_1]...gone?"},{"textLeft":"That was a decoy."},{"chara":[{"cheek":0,"face":"mtn_ex_050.exp.json","id":100300,"mouthOpen":0}],"textRight":"What?@Where are you?!"},{"autoTurnFirst":1.0,"bgEffect":"shakeLarge","chara":[{"cheek":0,"face":"mtn_ex_060.exp.json","id":100300,"motion":400,"mouthOpen":1}],"flashEffect":"flashWhiteSlow2","textRight":"Come out and...wah!"},{"bg":"bg_adv_12061.jpg","chara":[{"cheek":0,"face":"mtn_ex_050.exp.json","id":101100,"motion":0,"mouthOpen":0,"pos":0}],"nameLeft":"Kaede","textLeft":"She's been tied up with rope!","turnChangeIn":"whiteIn","turnChangeOut":"whiteOut"},{"chara":[{"cheek":0,"face":"mtn_ex_011.exp.json","id":101000,"motion":200,"mouthOpen":0,"pos":2}],"nameRight":"Momoko","textRight":"Yesss, Yachiyo wins!"},{"bg":"bg_adv_12061.jpg","chara":[{"cheek":0,"face":"mtn_ex_010.exp.json","id":100200,"motion":0,"mouthOpen":0,"pos":0},{"cheek":0,"face":"mtn_ex_060.exp.json","id":100300,"motion":0,"mouthOpen":0,"pos":2}],"nameLeft":"Yachiyo","nameRight":"Tsuruno","textLeft":"Sorry I tricked you.","turnChangeIn":"rollInFast","turnChangeOut":"rollOutFast"},{"chara":[{"cheek":0,"face":"mtn_ex_030.exp.json","id":100300,"mouthOpen":0}],"textRight":"I can't believe you caught me..."},{"chara":[{"cheek":0,"face":"mtn_ex_050.exp.json","id":100300,"motion":200,"mouthOpen":1}],"textRight":"Hah! I see... @[chara:100300:effect_emotion_surprise_0][se:7226_shock]You gave me the upper hand on purpose."},{"chara":[{"cheek":0,"face":"mtn_ex_030.exp.json","id":100200,"mouthOpen":0}],"textLeft":"It seemed the only way.@You're pretty strong..."},{"chara":[{"cheek":0,"face":"mtn_ex_030.exp.json","id":100300,"motion":0,"mouthOpen":0}],"textRight":"Urrrgggh...!"},{"chara":[{"cheek":0,"id":100300,"lipSynch":0,"mouthOpen":0}],"textRight":"(I can't break free...)","turnEffect":"thinking"},{"chara":[{"cheek":0,"face":"mtn_ex_001.exp.json","id":100300,"lipSynch":0,"mouthOpen":0}],"textRight":"Well, you've got me...","turnEffect":"stop"},{"chara":[{"cheek":0,"face":"mtn_ex_021.exp.json","id":100300,"mouthOpen":1}],"textRight":"Now finish the job!"},{"chara":[{"cheek":0,"face":"mtn_ex_050.exp.json","id":101000,"motion":200,"mouthOpen":0,"pos":0}],"nameLeft":"Momoko","textLeft":"It's already over!"},{"chara":[{"cheek":0,"face":"mtn_ex_020.exp.json","id":101100,"motion":100,"mouthOpen":0,"pos":2}],"nameRight":"Kaede","textRight":"Yeah, she won already!@Don't draw this out!"},{"chara":[{"cheek":0,"face":"mtn_ex_051.exp.json","id":100200,"motion":100,"mouthOpen":0,"pos":0}],"nameLeft":"Yachiyo","textLeft":"...Is that what you really want?"},{"chara":[{"cheek":0,"face":"mtn_ex_050.exp.json","id":100900,"motion":0,"mouthOpen":0,"pos":2}],"nameRight":"Rena","textRight":"No way...@...She wouldn't...would she?"},{"chara":[{"cheek":0,"face":"mtn_ex_021.exp.json","id":100200,"motion":200,"mouthOpen":0}],"textLeft":"Well then, I'll gladly finish the job..."},{"chara":[{"cheek":0,"face":"mtn_ex_050.exp.json","id":101000,"motion":200,"mouthOpen":0,"pos":2}],"nameRight":"Momoko","textRight":"Y-Yachiyo, wait!"},{"autoTurnLast":2.0,"turnChangeIn":"fadeIn"}]},"version":2}