{"story":{"group_1":[{"bg":"bg_adv_21241.jpg","bgm":"bgm03_story09","chara":[{"cheek":0,"face":"mtn_ex_050.exp.json","id":303001,"motion":1,"pos":0},{"cheek":0,"face":"mtn_ex_010.exp.json","id":301101,"motion":1,"pos":2}],"nameLeft":"Konomi","nameRight":"Kako","surround":"7102_townbuzz","textLeft":"Phew...@Good thing she wasn't too hard to beat.","turnChangeIn":"fadeIn","turnChangeOut":"fadeOut"},{"chara":[{"cheek":0,"face":"mtn_ex_010.exp.json","id":101101,"motion":0,"pos":2}],"nameRight":"Kaede","textRight":"It looks like we're only 30 minutes late@for the fair!"},{"chara":[{"cheek":0,"face":"mtn_ex_010.exp.json","id":303001,"motion":200}],"textLeft":"Okay! Let's get started while people@are still out and about!"},{"chara":[{"cheek":0,"face":"mtn_ex_010.exp.json","id":301101,"motion":1,"pos":2}],"nameRight":"Kako","textRight":"Right!"},{"chara":[{"cheek":0,"face":"mtn_ex_011.exp.json","id":303001,"motion":100}],"textLeft":"Let's try to sell everything!"},{"chara":[{"cheek":0,"face":"mtn_ex_011.exp.json","id":101101,"motion":100,"mouthOpen":1,"pos":2}],"nameRight":"Kaede","textRight":"All right![chara:101101:effect_emotion_joy_0][se:7222_happy]"},{"chara":[{"cheek":1,"face":"mtn_ex_030.exp.json","id":301101,"motion":400,"mouthOpen":1,"pos":2}],"textRight":"O-okay!"},{"chara":[{"cheek":0,"face":"mtn_ex_010.exp.json","id":101101,"motion":0,"pos":2},{"cheek":0,"face":"mtn_ex_010.exp.json","id":303001,"motion":1,"pos":0}],"nameLeft":"Konomi","nameRight":"Kaede","textLeft":"Welcome!@We've got the perfect birthday present!","turnChangeIn":"rollIn","turnChangeOut":"rollOut"},{"chara":[{"cheek":0,"face":"mtn_ex_010.exp.json","id":303001,"mouthOpen":1}],"textLeft":"It's a birthday cake made out of flowers!@How about it?"},{"chara":[{"cheek":0,"face":"mtn_ex_010.exp.json","id":101101,"motion":1}],"textRight":"A flower birthday cake!"},{"chara":[{"cheek":0,"face":"mtn_ex_011.exp.json","id":101101,"mouthOpen":1}],"textRight":"It comes with the birth flower's meaning!@Why not give one to a loved one?"},{"chara":[{"cheek":1,"face":"mtn_ex_010.exp.json","id":800100,"motion":0,"mouthOpen":1,"pos":2}],"nameRight":"","textRight":"Oh, they're so cute! Flower cakes!@Hey, wanna go take a look?"},{"chara":[{"cheek":1,"face":"mtn_ex_050.exp.json","id":303001,"lipSynch":0}],"textLeft":"(Yes!)"},{"chara":[{"cheek":0,"face":"mtn_ex_010.exp.json","id":801000,"motion":0,"pos":0},{"effect":"fadeout","id":800100}],"nameLeft":"","textLeft":"Wow...@A birthday cake made from flowers!"},{"chara":[{"cheek":0,"face":"mtn_ex_010.exp.json","id":801000}],"textLeft":"I need to get a birthday present...@Maybe I'll just get this!"},{"chara":[{"cheek":0,"face":"mtn_ex_010.exp.json","id":801000}],"textLeft":"Excuse me, are the candies included?"},{"chara":[{"cheek":1,"face":"mtn_ex_050.exp.json","id":301101,"motion":400,"pos":2}],"nameRight":"Kako","textRight":"Ah, [chara:301101:effect_emotion_surprise_0][se:7226_shock]y-yes!"},{"chara":[{"cheek":1,"face":"mtn_ex_030.exp.json","id":301101,"motion":100}],"textRight":"The candies are@actually inside the cake!"},{"chara":[{"cheek":1,"face":"mtn_ex_011.exp.json","id":801000}],"textLeft":"Oh, wow! Seriously?!@That's even cooler than I thought!"},{"chara":[{"cheek":0,"face":"mtn_ex_010.exp.json","id":801000}],"textLeft":"Okay, then!@I'll take one, please!"},{"chara":[{"cheek":1,"face":"mtn_ex_050.exp.json","id":301101}],"textRight":"Oh!@R-right! [chara:301101:motion_400]Here you go!"},{"chara":[{"cheek":0,"face":"mtn_ex_011.exp.json","id":303001,"motion":1,"pos":0}],"nameLeft":"Konomi","textLeft":"Yay!"},{"chara":[{"cheek":1,"face":"mtn_ex_050.exp.json","id":301101,"motion":300}],"textRight":"Yeah! Yay!"},{"bgm":"bgm04_movie08","chara":[{"cheek":1,"face":"mtn_ex_050.exp.json","id":303001,"motion":0,"pos":0},{"cheek":0,"face":"mtn_ex_010.exp.json","id":801100,"motion":0,"pos":2}],"nameLeft":"Konomi","nameRight":"","surround":"stop","textRight":"Ummm, I'd like this...pansy cake?","turnChangeIn":"rollIn","turnChangeOut":"rollOut"},{"chara":[{"cheek":1,"face":"mtn_ex_050.exp.json","id":303001,"motion":1}],"textLeft":"Okay![chara:303001:cheek_1:face_mtn_ex_010.exp.json] Right away!"},{"chara":[{"cheek":1,"face":"mtn_ex_050.exp.json","id":101101,"motion":100,"mouthOpen":1,"pos":2}],"nameRight":"Kaede","textRight":"Customers looking for a flower@birthday cake..."},{"chara":[{"cheek":1,"face":"mtn_ex_050.exp.json","id":101101,"mouthOpen":1}],"textRight":"Please line up here!"},{"chara":[{"cheek":1,"face":"mtn_ex_030.exp.json","id":301101,"motion":400,"pos":2}],"nameRight":"Kako","textRight":"Okay, the end of the line is this way!"},{"chara":[{"cheek":1,"face":"mtn_ex_050.exp.json","id":303001,"motion":301}],"textLeft":"It's never been this busy before!"},{"chara":[{"cheek":1,"face":"mtn_ex_050.exp.json","id":301101,"motion":100}],"textRight":"I can't believe how many people there are!"},{"chara":[{"cheek":1,"face":"mtn_ex_050.exp.json","id":101101,"motion":1,"pos":2}],"nameRight":"Kaede","textRight":"It's amazing!"},{"chara":[{"cheek":0,"face":"mtn_ex_010.exp.json","id":101101}],"textRight":"Looks like we can say our@plan was a big success, huh?"},{"chara":[{"cheek":1,"face":"mtn_ex_011.exp.json","id":303001,"motion":100}],"textLeft":"It sure was!"},{"bg":"bg_adv_21082.jpg","bgm":"stop","chara":[{"cheek":1,"face":"mtn_ex_011.exp.json","id":303001,"motion":200,"mouthOpen":1,"pos":0},{"cheek":0,"face":"mtn_ex_010.exp.json","id":101101,"motion":0,"pos":2}],"nameLeft":"Konomi","nameRight":"Kaede","textLeft":"Congratulations! Everything sold!","turnChangeIn":"fadeIn","turnChangeOut":"fadeOut"},{"chara":[{"cheek":1,"face":"mtn_ex_010.exp.json","id":301101,"motion":300,"pos":2}],"nameRight":"Kako","textRight":"Congratulations!"},{"chara":[{"cheek":0,"face":"mtn_ex_011.exp.json","id":101101,"motion":0,"pos":2}],"nameRight":"Kaede","textRight":"We did it!"},{"chara":[{"cheek":0,"face":"mtn_ex_010.exp.json","id":303001,"motion":0}],"textLeft":"And when Auntie came to,@the shop was packed with people..."},{"chara":[{"cheek":1,"face":"mtn_ex_011.exp.json","id":303001,"motion":400}],"textLeft":"She was super surprised!"},{"chara":[{"cheek":1,"face":"mtn_ex_010.exp.json","id":301101,"motion":100,"pos":2}],"nameRight":"Kako","textRight":"Hehehe. Yeah, yeah!"},{"chara":[{"cheek":0,"face":"mtn_ex_010.exp.json","id":303001,"motion":0}],"textLeft":"Ah! Here! I made these for you two..."},{"chara":[{"cheek":0,"face":"mtn_ex_050.exp.json","id":101101,"motion":0,"pos":2}],"nameRight":"Kaede","textRight":"Flower cakes!"},{"bgm":"bgm03_story05","chara":[{"cheek":1,"face":"mtn_ex_030.exp.json","id":301101,"motion":1,"pos":2}],"nameRight":"Kako","textRight":"Really? Are you sure?@It's not our birthday..."},{"chara":[{"cheek":1,"face":"mtn_ex_010.exp.json","id":303001}],"textLeft":"That's okay...@[chara:303001:motion_301:cheek_1:face_mtn_ex_030.exp.json]You two stuck by me through all my problems."},{"chara":[{"cheek":1,"id":303001}],"textLeft":"You helped me so much...@[chara:303001:cheek_1:face_mtn_ex_010.exp.json:motion_001]This is just my way of saying thanks."},{"chara":[{"cheek":1,"face":"mtn_ex_030.exp.json","id":301101}],"textRight":"Konomi..."},{"chara":[{"cheek":0,"face":"mtn_ex_010.exp.json","id":303001,"motion":0}],"textLeft":"Besides, these aren't your birth flowers."},{"chara":[{"cheek":0,"face":"mtn_ex_050.exp.json","id":101101,"motion":0,"mouthOpen":1,"pos":2}],"nameRight":"Kaede","textRight":"Huh?@So what are they?"},{"chara":[{"cheek":0,"face":"mtn_ex_010.exp.json","id":303001,"motion":1}],"textLeft":"It's a message from me to the both of you."},{"chara":[{"cheek":0,"face":"mtn_ex_030.exp.json","id":301101,"motion":100,"mouthOpen":1,"pos":2}],"nameRight":"Kako","textRight":"These flowers... They're geraniums..."},{"chara":[{"cheek":0,"face":"mtn_ex_050.exp.json","id":101101,"motion":1,"mouthOpen":1,"pos":2}],"nameRight":"Kaede","textRight":"Geraniums represent..."},{"chara":[{"cheek":0,"face":"mtn_ex_030.exp.json","id":301101,"motion":300,"mouthOpen":1,"pos":2}],"nameRight":"Kako","textRight":"Respect..."},{"chara":[{"cheek":0,"face":"mtn_ex_050.exp.json","id":101101,"motion":1,"mouthOpen":1,"pos":2}],"nameRight":"Kaede","textRight":"Trust..."},{"chara":[{"cheek":0,"face":"mtn_ex_010.exp.json","id":303001,"motion":0}],"textLeft":"True friendship..."},{"chara":[{"cheek":1,"face":"mtn_ex_030.exp.json","id":303001,"motion":1}],"textLeft":"Thank you so much for what you've done."},{"chara":[{"cheek":2,"face":"mtn_ex_010.exp.json","id":303001}],"textLeft":"And...[chara:303001:motion_000]I hope we can be close like this@forever, okay?"},{"chara":[{"cheek":1,"face":"mtn_ex_050.exp.json","id":101101,"mouthOpen":1}],"textRight":"Oh, Konomi!@[chara:101101:cheek_2:face_mtn_ex_030.exp.json]Thank you! Thank you so much!"},{"chara":[{"cheek":2,"face":"mtn_ex_030.exp.json","id":301101,"motion":100,"mouthOpen":1,"pos":2}],"nameRight":"Kako","textRight":"Thank you!@I'll treasure it forever!"},{"chara":[{"cheek":2,"face":"mtn_ex_011.exp.json","id":301101,"motion":300}],"nameNarration":"Konomi","narration":"And that's it…@The beginning of our [freeze:1]story.","narrationBg":"bg_adv_11022.jpg","narrationEffect":"in"},{"autoTurnFirst":3.3,"bg":"bg_adv_narration.jpg","bgm":"stop","chara":[{"cheek":0,"face":"mtn_ex_010.exp.json","id":303001,"motion":1,"pos":1,"voice":"vo_char_3030_00_05"}],"nameCenter":"Konomi","narrationEffect":"out","textCenter":"There's no time to stop!@The customers are waiting for us!","turnChangeIn":"fadeIn","turnChangeOut":"fadeOut","turnEffect":"stop"},{"autoTurnFirst":1.0,"chara":[{"id":303001,"motion":200}]},{"autoTurnFirst":2.0,"chara":[{"cheek":0,"face":"mtn_ex_011.exp.json","id":303001}]},{"chara":[{"id":303001}]},{"autoTurnLast":2.0,"turnChangeIn":"fadeIn"}]},"version":3}