{
    "story": {
        "group_1": [
            {
                "autoTurnLast": 0.01,
                "bg": "bg_adv_13024.jpg",
                "chara": [
                    {
                        "cheek": 0,
                        "face": "mtn_ex_050.exp.json",
                        "id": 100100,
                        "motion": 0,
                        "pos": 0
                    },
                    {
                        "cheek": 0,
                        "face": "mtn_ex_020.exp.json",
                        "id": 100400,
                        "motion": 0,
                        "pos": 2
                    }
                ],
                "turnChangeIn": "fadeIn"
            },
            {
                "bgm": "bgm01_battle13",
                "chara": [
                    {
                        "id": 100100,
                        "motion": 401,
                        "voiceFull": "fullvoice/section_102002/vo_full_102002-8-1"
                    }
                ],
                "nameLeft": "Iroha",
                "nameRight": "Sana",
                "textLeft": "Let you handle this? Sana, what are you...",
                "turnChangeOut": "fadeOut"
            },
            {
                "chara": [
                    {
                        "id": 100400,
                        "motion": 200,
                        "voiceFull": "fullvoice/section_102002/vo_full_102002-8-2",
                        "voiceFullStop": "fullvoice/section_102002/vo_full_102002-8-1"
                    }
                ],
                "textRight": "I can lock it in place with my chains!"
            },
            {
                "chara": [
                    {
                        "id": 100400,
                        "voiceFull": "fullvoice/section_102002/vo_full_102002-8-3",
                        "voiceFullStop": "fullvoice/section_102002/vo_full_102002-8-2"
                    }
                ],
                "textRight": "Hurry and search for its weakness while I@keep it still!"
            },
            {
                "chara": [
                    {
                        "cheek": 0,
                        "face": "mtn_ex_000.exp.json",
                        "id": 200600,
                        "motion": 1,
                        "pos": 0,
                        "voiceFull": "fullvoice/section_102002/vo_full_102002-8-4",
                        "voiceFullStop": "fullvoice/section_102002/vo_full_102002-8-3"
                    },
                    {
                        "cheek": 0,
                        "face": "mtn_ex_040.exp.json",
                        "id": 100400,
                        "motion": 0
                    }
                ],
                "nameLeft": "Kyoko",
                "textLeft": "You gonna do that all on your own?"
            },
            {
                "chara": [
                    {
                        "cheek": 0,
                        "face": "mtn_ex_010.exp.json",
                        "id": 200600,
                        "voiceFull": "fullvoice/section_102002/vo_full_102002-8-5",
                        "voiceFullStop": "fullvoice/section_102002/vo_full_102002-8-4"
                    }
                ],
                "textLeft": "I tell ya, it's always the ones who look@like weaklin's who've got the biggest guts."
            },
            {
                "chara": [
                    {
                        "id": 200600,
                        "motion": 100,
                        "voiceFull": "fullvoice/section_102002/vo_full_102002-8-6",
                        "voiceFullStop": "fullvoice/section_102002/vo_full_102002-8-5"
                    }
                ],
                "textLeft": "Here, I'll help ya out."
            },
            {
                "chara": [
                    {
                        "cheek": 0,
                        "face": "mtn_ex_001.exp.json",
                        "id": 200500,
                        "motion": 200,
                        "pos": 0,
                        "voiceFull": "fullvoice/section_102002/vo_full_102002-8-7",
                        "voiceFullStop": "fullvoice/section_102002/vo_full_102002-8-6"
                    }
                ],
                "nameLeft": "Mami",
                "textLeft": "I will, too!"
            },
            {
                "chara": [
                    {
                        "cheek": 0,
                        "face": "mtn_ex_010.exp.json",
                        "id": 200500,
                        "voiceFull": "fullvoice/section_102002/vo_full_102002-8-8",
                        "voiceFullStop": "fullvoice/section_102002/vo_full_102002-8-7"
                    }
                ],
                "textLeft": "We're trying to restrain a truly monstrous@Witch."
            },
            {
                "chara": [
                    {
                        "cheek": 0,
                        "face": "mtn_ex_010.exp.json",
                        "id": 200500,
                        "motion": 100,
                        "voiceFull": "fullvoice/section_102002/vo_full_102002-8-9",
                        "voiceFullStop": "fullvoice/section_102002/vo_full_102002-8-8"
                    }
                ],
                "textLeft": "The more help you have the better, correct?"
            },
            {
                "chara": [
                    {
                        "cheek": 0,
                        "face": "mtn_ex_010.exp.json",
                        "id": 100400,
                        "motion": 100,
                        "voiceFull": "fullvoice/section_102002/vo_full_102002-8-10",
                        "voiceFullStop": "fullvoice/section_102002/vo_full_102002-8-9"
                    }
                ],
                "textRight": "Ohhh! Thank you both so much!"
            },
            {
                "chara": [
                    {
                        "cheek": 0,
                        "face": "mtn_ex_020.exp.json",
                        "id": 200500,
                        "motion": 200,
                        "voiceFull": "fullvoice/section_102002/vo_full_102002-8-11",
                        "voiceFullStop": "fullvoice/section_102002/vo_full_102002-8-10"
                    }
                ],
                "textLeft": "Everyone, please!"
            },
            {
                "chara": [
                    {
                        "id": 200500,
                        "voiceFull": "fullvoice/section_102002/vo_full_102002-8-12",
                        "voiceFullStop": "fullvoice/section_102002/vo_full_102002-8-11"
                    }
                ],
                "textLeft": "Help us secure the ribbons and chains to the@ground!"
            },
            {
                "chara": [
                    {
                        "cheek": 0,
                        "face": "mtn_ex_020.exp.json",
                        "id": 200100,
                        "motion": 100,
                        "pos": 2,
                        "voiceFull": "fullvoice/section_102002/vo_full_102002-8-13",
                        "voiceFullStop": "fullvoice/section_102002/vo_full_102002-8-12"
                    }
                ],
                "nameRight": "Madoka",
                "textRight": "Got it!"
            },
            {
                "chara": [
                    {
                        "cheek": 0,
                        "face": "mtn_ex_021.exp.json",
                        "id": 100100,
                        "motion": 400,
                        "pos": 0,
                        "voiceFull": "fullvoice/section_102002/vo_full_102002-8-14",
                        "voiceFullStop": "fullvoice/section_102002/vo_full_102002-8-13"
                    }
                ],
                "nameLeft": "Iroha",
                "textLeft": "Yes! Let's pin Eve down with our arrows,@Madoka!"
            },
            {
                "chara": [
                    {
                        "id": 200100,
                        "motion": 201,
                        "voiceFull": "fullvoice/section_102002/vo_full_102002-8-15",
                        "voiceFullStop": "fullvoice/section_102002/vo_full_102002-8-14"
                    }
                ],
                "textRight": "Okay!"
            },
            {
                "chara": [
                    {
                        "cheek": 0,
                        "face": "mtn_ex_021.exp.json",
                        "id": 100200,
                        "motion": 0,
                        "pos": 0
                    },
                    {
                        "cheek": 0,
                        "face": "mtn_ex_050.exp.json",
                        "id": 100500,
                        "motion": 0,
                        "pos": 2,
                        "voiceFull": "fullvoice/section_102002/vo_full_102002-8-16",
                        "voiceFullStop": "fullvoice/section_102002/vo_full_102002-8-15"
                    }
                ],
                "nameLeft": "Yachiyo",
                "nameRight": "Felicia",
                "textRight": "What should I do?!"
            },
            {
                "chara": [
                    {
                        "id": 100500,
                        "motion": 200,
                        "voiceFull": "fullvoice/section_102002/vo_full_102002-8-17",
                        "voiceFullStop": "fullvoice/section_102002/vo_full_102002-8-16"
                    }
                ],
                "textRight": "I have a hammer. All I do is bash stuff."
            },
            {
                "chara": [
                    {
                        "id": 100200,
                        "motion": 201,
                        "voiceFull": "fullvoice/section_102002/vo_full_102002-8-18",
                        "voiceFullStop": "fullvoice/section_102002/vo_full_102002-8-17"
                    }
                ],
                "textLeft": "I'll generate some spears. You can use those."
            },
            {
                "chara": [
                    {
                        "id": 100500,
                        "motion": 400,
                        "voiceFull": "fullvoice/section_102002/vo_full_102002-8-19",
                        "voiceFullStop": "fullvoice/section_102002/vo_full_102002-8-18"
                    }
                ],
                "textRight": "Oooh!"
            },
            {
                "chara": [
                    {
                        "cheek": 0,
                        "face": "mtn_ex_010.exp.json",
                        "id": 100500,
                        "motion": 200,
                        "voiceFull": "fullvoice/section_102002/vo_full_102002-8-20",
                        "voiceFullStop": "fullvoice/section_102002/vo_full_102002-8-19"
                    }
                ],
                "textRight": "Nice! I get to chuck spears around!"
            },
            {
                "chara": [
                    {
                        "cheek": 0,
                        "face": "mtn_ex_001.exp.json",
                        "id": 100300,
                        "motion": 200,
                        "pos": 0,
                        "voiceFull": "fullvoice/section_102002/vo_full_102002-8-21",
                        "voiceFullStop": "fullvoice/section_102002/vo_full_102002-8-20"
                    }
                ],
                "nameLeft": "Tsuruno",
                "textLeft": "Don't hog all of them for yourself, Felicia!"
            },
            {
                "autoTurnLast": 2,
                "turnChangeIn": "fadeIn",
                "voiceFullStop": "fullvoice/section_102002/vo_full_102002-8-21"
            }
        ]
    },
    "version": 3
}