{"story":{"group_1":[{"bg":"bg_adv_11021.jpg","bgm":"bgm01_anime03","chara":[{"cheek":0,"face":"mtn_ex_010.exp.json","id":301101,"motion":1,"pos":2},{"cheek":0,"face":"mtn_ex_010.exp.json","id":200150,"motion":0,"pos":0}],"nameLeft":"Madoka","nameRight":"Kako","textRight":"Do you know about the Chocolate of Fate,@Madoka?","turnChangeIn":"fadeIn","turnChangeOut":"fadeOut"},{"chara":[{"cheek":0,"face":"mtn_ex_040.exp.json","id":200150}],"textLeft":"Chocolate of...Fate?"},{"chara":[{"id":301101,"motion":400}],"textRight":"Yes! There's a rumor going around all the@schools."},{"chara":[{"id":301101}],"textRight":"They say there's a secret sweets store@that randomly appears in Kamihama."},{"chara":[{"id":301101}],"textRight":"And that you can buy chocolate there that@has your fate copied onto it!"},{"chara":[{"cheek":0,"face":"mtn_ex_051.exp.json","id":200150,"motion":0}],"textLeft":"My fate? Like fortune telling?"},{"chara":[{"id":200150}],"textLeft":"Is it chocolate for Valentine's Day?"},{"chara":[{"eyeClose":1,"id":301101,"motion":0}],"textRight":"The rumor says you can exchange your@Chocolate of Fate with someone else..."},{"chara":[{"id":301101}],"textRight":"...or just give the whole thing away."},{"chara":[{"eyeClose":0,"id":301101}],"textRight":"I heard it's also perfect for Valentine's @Day."},{"chara":[{"id":301101,"motion":400}],"textRight":"Some people claim their lives changed@drastically because of it."},{"chara":[{"cheek":0,"face":"mtn_ex_040.exp.json","id":200150,"motion":0}],"textLeft":"Really?"},{"chara":[{"id":301101,"motion":200}],"textRight":"And that's not all! This came in the mail@the other day!"},{"chara":[{"id":301101}],"textRight":"\"Chocolate of Fate On Sale!@The low, low price of 500 yen!\""},{"chara":[{"cheek":0,"face":"mtn_ex_051.exp.json","id":200150,"motion":400}],"textLeft":"[chara:200150:effect_emotion_surprise_0][se:7226_shock]Th-they send out flyers?!"},{"chara":[{"cheek":0,"face":"mtn_ex_040.exp.json","id":200150,"motion":0}],"textLeft":"That's a bit too much. I'm kinda suspicious@now."},{"chara":[{"cheek":0,"face":"mtn_ex_011.exp.json","id":301101,"motion":0}],"textRight":"Same here... It's just common sense to@think this a prank."},{"chara":[{"cheek":0,"face":"mtn_ex_022.exp.json","id":301101}],"textRight":"But I'd like to check it out just in case!"},{"chara":[{"id":301101,"motion":400}],"textRight":"It won't take long, I promise! We could go@while we're out shopping..."},{"chara":[{"id":301101}],"textRight":"I'd really like for us to go there and take@a quick look!"},{"chara":[{"id":301101,"motion":0}],"textRight":"And if they're suspicious looking, then..."},{"chara":[{"id":301101}],"textRight":"...we'll just transform someplace quiet@and kick their butts!"},{"chara":[{"cheek":0,"face":"mtn_ex_041.exp.json","id":200150,"lipSynch":0,"motion":201}],"textLeft":"(Note to self: Kako might actually be pretty @fierce...)"},{"bg":"bg_adv_19021.jpg","chara":[{"cheek":0,"face":"mtn_ex_010.exp.json","id":200150,"motion":100,"pos":0},{"cheek":0,"face":"mtn_ex_010.exp.json","id":301101,"motion":0,"pos":2}],"textLeft":"The map on the flyer says it should be@around here somewhere.","turnChangeIn":"fadeIn","turnChangeOut":"fadeOut"},{"chara":[{"cheek":0,"face":"mtn_ex_040.exp.json","id":200150}],"textLeft":"But I don't see a single store anywhere.@This is just getting more suspicious..."},{"chara":[{"id":301101,"motion":400}],"textRight":"Oh! It's that building there."},{"chara":[{"cheek":0,"face":"mtn_ex_040.exp.json","id":200150,"motion":0}],"textLeft":"The store name's a match, too.@Chocolat...Shop?"},{"chara":[{"id":301101,"motion":1}],"textRight":"That's the French spelling of \"chocolate\"."},{"bg":"bg_adv_20151.jpg","chara":[{"cheek":0,"face":"mtn_ex_050.exp.json","id":301101,"motion":0,"pos":2},{"cheek":0,"face":"mtn_ex_040.exp.json","id":200150,"motion":0,"pos":0}],"textRight":"It's like a maze in here. Not exactly what@you expect inside a store.","turnChangeIn":"fadeIn","turnChangeOut":"fadeOut"},{"chara":[{"id":200150,"motion":201}],"textLeft":"Yeah, this is really strange."},{"chara":[{"id":200150}],"textLeft":"Could it be an elaborate prank?"},{"chara":[{"cheek":0,"face":"mtn_ex_030.exp.json","id":301101,"motion":100}],"textRight":"I suppose..."},{"chara":[{"id":301101}],"textRight":"I'm sorry, this is taking much longer than @I thought it would..."},{"chara":[{"cheek":0,"face":"mtn_ex_010.exp.json","id":200150,"motion":1}],"textLeft":"Oh, don't worry about that!"},{"chara":[{"id":200150}],"textLeft":"I was really curious about this. It would've@bothered me if I didn't check it out."},{"chara":[{"cheek":0,"face":"mtn_ex_011.exp.json","id":200150}],"textLeft":"It's fun, even! It's like we're lost in a@treasure maze!"},{"chara":[{"cheek":0,"face":"mtn_ex_010.exp.json","id":301101,"motion":0}],"textRight":"Madoka, what would you do if the@Chocolate of Fate were real?"},{"chara":[{"cheek":0,"face":"mtn_ex_030.exp.json","id":200150,"motion":0}],"textLeft":"Well..."},{"chara":[{"cheek":0,"face":"mtn_ex_040.exp.json","id":200150}],"textLeft":"I can't think who I'd give it to, but..."},{"chara":[{"id":200150}],"textLeft":"...I do check my fortune often."},{"chara":[{"cheek":0,"face":"mtn_ex_010.exp.json","id":200150,"motion":100}],"textLeft":"And I guess I am a bit curious how my fate@has been turning out!"},{"chara":[{"id":200150}],"textLeft":"What about you? Would you give it to@someone?"},{"chara":[{"cheek":0,"face":"mtn_ex_011.exp.json","id":301101,"motion":1}],"textRight":"No, there's no one for me to give it to yet."},{"chara":[{"cheek":0,"face":"mtn_ex_030.exp.json","id":301101}],"textRight":"But, I wonder about my fate too."},{"chara":[{"id":301101}],"textRight":"Don't you think that, if there really were@chocolate with your fate on it..."},{"chara":[{"cheek":0,"face":"mtn_ex_011.exp.json","id":301101,"motion":400}],"textRight":"...and you broke it to smithereens, you@might be able to become a new you?"},{"chara":[{"id":301101}],"textRight":"I've been thinking about how I became@a Magical Girl..."},{"chara":[{"id":301101,"motion":0}],"textRight":"I think I've managed to change, but only @a little."},{"chara":[{"cheek":0,"face":"mtn_ex_030.exp.json","id":301101}],"textRight":"Maybe I should be trying harder."},{"chara":[{"id":200150,"motion":0}],"textLeft":"I think you're fine the way you are, Kako."},{"bgm":"stop","chara":[{"id":301101,"lipSynch":0}],"textRight":"..."},{"chara":[{"cheek":0,"face":"mtn_ex_011.exp.json","id":301101}],"textRight":"I've been...seeing the same dream recently."},{"bgm":"bgm03_story06","chara":[{"id":301101}],"textRight":"In it, I'm a Magical Girl, but a monster @emerges from my body, and it's not me."},{"chara":[{"eyeClose":1,"id":301101}],"textRight":"It destroys not only my precious books, but@everything else."},{"chara":[{"id":301101,"motion":300}],"textRight":"In my dream, it tears up everything and leaves@it in shambles..."},{"chara":[{"cheek":0,"face":"mtn_ex_030.exp.json","id":200150,"lipSynch":0}],"textLeft":"..."},{"chara":[{"id":301101}],"textRight":"But..."},{"chara":[{"eyeClose":0,"id":301101}],"textRight":"I wasn't sad...even though I should be.@In fact I felt something much worse."},{"chara":[{"cheek":0,"face":"mtn_ex_010.exp.json","id":301101,"motion":0}],"textRight":"If I don't change..."},{"chara":[{"cheek":0,"face":"mtn_ex_011.exp.json","id":301101}],"textRight":"What if one day..."},{"chara":[{"id":301101}],"textRight":"...I actually become like that?"},{"chara":[{"eyeClose":1,"id":301101}],"textRight":"That's why I have to take my fate into my@own hands."},{"chara":[{"eyeClose":0,"id":301101,"motion":100}],"textRight":"I guess you could say I'm being@superstitious..."},{"chara":[{"id":301101,"motion":200}],"textRight":"It's just a dream, but it's scaring me@so much."},{"chara":[{"id":301101}],"textRight":"Do you think it's weird?"},{"chara":[{"cheek":0,"face":"mtn_ex_010.exp.json","id":200150,"motion":1}],"textLeft":"Of course not. It's not weird at all."},{"chara":[{"cheek":0,"face":"mtn_ex_030.exp.json","id":200150}],"textLeft":"Actually, I also have dreams where I become@some kind of monster."},{"chara":[{"id":200150}],"textLeft":"I have them often, too..."},{"chara":[{"eyeClose":1,"id":200150}],"textLeft":"Who knows? Maybe some day, unexpectedly..."},{"chara":[{"id":200150}],"textLeft":"I might lose myself and become it."},{"chara":[{"id":200150,"motion":0}],"textLeft":"It scares me, too."},{"chara":[{"cheek":0,"eyeClose":0,"face":"mtn_ex_010.exp.json","id":200150}],"textLeft":"So, I get you."},{"chara":[{"cheek":0,"face":"mtn_ex_011.exp.json","id":200150,"motion":100}],"textLeft":"But anyway!"},{"chara":[{"id":200150}],"textLeft":"If the Chocolate of Fate really exists,@I'm taking it."},{"chara":[{"cheek":0,"face":"mtn_ex_010.exp.json","id":200150}],"textLeft":"Then I'll melt it all up and make it@bite-sized for all my friends!"},{"autoTurnLast":2.0,"turnChangeIn":"fadeIn"}]},"version":3}