{"story":{"group_1":[{"autoTurnLast":0.5,"bg":"bg_adv_21242.jpg","chara":[{"cheek":0,"face":"mtn_ex_030.exp.json","id":303001,"motion":0,"pos":0},{"cheek":0,"face":"mtn_ex_000.exp.json","id":101601,"motion":0,"pos":2}],"turnChangeIn":"fadeIn"},{"bgm":"bgm03_story02","chara":[{"id":303001,"motion":301}],"nameLeft":"Konomi","textLeft":"First though...I need to apologize.","turnChangeOut":"fadeOut"},{"chara":[{"cheek":0,"face":"mtn_ex_050.exp.json","id":101601,"motion":200}],"nameRight":"Kanagi","textRight":"Hm? Why is that?"},{"chara":[{"cheek":0,"face":"mtn_ex_050.exp.json","id":303001,"motion":1}],"textLeft":"It's just, Nagitan... Oops, I mean..."},{"chara":[{"cheek":0,"face":"mtn_ex_030.exp.json","id":303001}],"textLeft":"I'm sorry. I can't get that nickname out@of my head."},{"chara":[{"cheek":0,"face":"mtn_ex_010.exp.json","id":101601,"motion":100}],"textRight":"Nagitan is fine. I like my nickname."},{"chara":[{"cheek":0,"face":"mtn_ex_050.exp.json","id":303001,"motion":0}],"textLeft":"Really?! Uh, okay then...Nagitan."},{"chara":[{"id":101601,"motion":0}],"textRight":"Yes?"},{"chara":[{"id":303001,"motion":301}],"textLeft":"Well...I had heard a lot about you."},{"chara":[{"id":303001}],"textLeft":"I thought you were a scary person."},{"chara":[{"cheek":0,"face":"mtn_ex_030.exp.json","id":303001}],"textLeft":"I thought that if I was too friendly with@you, um...you might get mad at me."},{"chara":[{"cheek":0,"face":"mtn_ex_030.exp.json","id":101601,"motion":300}],"textRight":"Because of all that happened between@the east and west."},{"chara":[{"id":303001}],"textLeft":"Yes..."},{"chara":[{"cheek":0,"face":"mtn_ex_022.exp.json","id":303001,"motion":0}],"textLeft":"But I shouldn't believe everything I hear@about someone before meeting them."},{"chara":[{"cheek":0,"face":"mtn_ex_010.exp.json","id":303001}],"textLeft":"I didn't know you were so friendly."},{"chara":[{"cheek":0,"face":"mtn_ex_030.exp.json","id":303001,"motion":301}],"textLeft":"I'm sorry I assumed things about you based@on rumors."},{"chara":[{"cheek":0,"face":"mtn_ex_050.exp.json","id":101601,"lipSynch":0,"motion":0}],"textRight":"..."},{"chara":[{"cheek":0,"face":"mtn_ex_010.exp.json","id":101601,"lipSynch":1,"motion":200}],"textRight":"No, it's fine."},{"chara":[{"id":101601}],"textRight":"I'm glad you saw the real me, despite what@you may have heard."},{"chara":[{"cheek":0,"face":"mtn_ex_010.exp.json","id":303001,"motion":0}],"textLeft":"You're really kind, too."},{"chara":[{"cheek":0,"face":"mtn_ex_030.exp.json","id":303001,"motion":1}],"textLeft":"To be honest, I went in there without@realizing it was a maid cafe."},{"chara":[{"id":303001}],"textLeft":"So I was really nervous."},{"chara":[{"cheek":0,"face":"mtn_ex_010.exp.json","id":303001,"motion":100}],"textLeft":"But now, I understand you were being@very considerate to me, Nagitan."},{"chara":[{"cheek":0,"face":"mtn_ex_050.exp.json","id":101601,"motion":100}],"textRight":"Considerate? Do you really think so?"},{"chara":[{"cheek":0,"eyeClose":0,"face":"mtn_ex_011.exp.json","id":303001,"motion":200}],"textLeft":"I do!"},{"chara":[{"cheek":0,"face":"mtn_ex_010.exp.json","id":303001}],"textLeft":"When I showed an interest in herbal tea,@you were helpful with suggestions."},{"chara":[{"id":303001}],"textLeft":"And you tried to ease my anxiety by@offering to play a game."},{"chara":[{"id":303001,"motion":1}],"textLeft":"I realized you were trying to make me more@comfortable being there."},{"chara":[{"cheek":0,"face":"mtn_ex_030.exp.json","id":303001}],"textLeft":"I'm not used to cafes like that so I won't@be going again, but..."},{"chara":[{"cheek":0,"face":"mtn_ex_010.exp.json","id":303001}],"textLeft":"The experience wasn't unpleasant thanks@to you."},{"chara":[{"cheek":0,"face":"mtn_ex_030.exp.json","id":101601,"lipSynch":0,"motion":0}],"textRight":"..."},{"chara":[{"id":101601,"lipSynch":1,"motion":300}],"textRight":"I was only doing my job."},{"chara":[{"id":101601}],"textRight":"None of that was actually my intention."},{"chara":[{"cheek":0,"face":"mtn_ex_050.exp.json","id":303001,"motion":0}],"textLeft":"Really?"},{"chara":[{"cheek":0,"face":"mtn_ex_010.exp.json","id":303001}],"textLeft":"Either way, I was still happy."},{"chara":[{"id":303001}],"textLeft":"Even if it wasn't what you meant to do,@it felt like you were doing it for me."},{"chara":[{"eyeClose":1,"id":303001,"motion":301}],"textLeft":"It was like you were being considerate of@how I felt."},{"bgm":"stop","chara":[{"cheek":0,"face":"mtn_ex_000.exp.json","id":101601,"lipSynch":0,"motion":0}],"textRight":"(Being considerate of another's feelings...)","turnEffect":"thinking"},{"chara":[{"id":101601,"lipSynch":0,"motion":200}],"textRight":"(In other words, thinking about what the@other person wants and responding to it.)"},{"bgm":"bgm03_story15","chara":[{"id":101601,"lipSynch":0}],"textRight":"([chara:101601:cheek_0][chara:101601:face_mtn_ex_050.exp.json]That's what the manager was getting at.)"},{"chara":[{"id":101601,"lipSynch":0,"motion":400}],"textRight":"(How considerate I'm being towards my@master...)"},{"chara":[{"cheek":0,"face":"mtn_ex_030.exp.json","id":101601,"lipSynch":0,"motion":300}],"textRight":"(It was my duty to always keep that in@mind.)"},{"chara":[{"eyeClose":1,"id":101601,"lipSynch":0}],"textRight":"(That's what I was lacking.)"},{"chara":[{"eyeClose":0,"id":303001,"motion":200}],"textLeft":"You may not be like the other maids,@Nagitan.","turnEffect":"stop"},{"chara":[{"id":303001}],"textLeft":"But I think you're good with customers."},{"chara":[{"cheek":0,"eyeClose":0,"face":"mtn_ex_050.exp.json","id":101601,"lipSynch":1,"motion":0}],"textRight":"...You do?"},{"chara":[{"cheek":0,"face":"mtn_ex_011.exp.json","id":303001,"motion":400}],"textLeft":"Yes!"},{"chara":[{"id":303001}],"textLeft":"You're a natural at taking care of people."},{"chara":[{"cheek":0,"face":"mtn_ex_010.exp.json","id":303001,"motion":100}],"textLeft":"So...keep up the good work!"},{"chara":[{"cheek":0,"face":"mtn_ex_030.exp.json","id":101601,"lipSynch":0}],"textRight":"..."},{"chara":[{"cheek":0,"face":"mtn_ex_010.exp.json","id":101601,"lipSynch":1,"motion":100}],"textRight":"I will do my best... Thanks for the help."},{"autoTurnLast":2.0,"bgm":"stop","turnChangeIn":"fadeIn"}]},"version":3}